<ModuleInfoEntry>
    <Module Name="FreeImage" Type="SharedLibrary" Platform="mswin;linux">
        <Preprocessor>
            <Define String="FREEIMAGE_EXPORTS" />
            <Define String="OPJ_STATIC" />
            <Define String="ZENO_STATIC" />
            <Define String="LIBRAW_LIBRARY_BUILD" />
            <Define String="NO_JASPER" />
            <Define String="USE_JPIP" />
	    <Define String="LIBRAW_NODLL" />
        </Preprocessor>
        <Dependencies>
            <Dependency Name="zlib" />
        </Dependencies>
        <Linker>
            <Dependency Name="zlib" />
        </Linker>
    </Module>
    <Module Platform="mswin">
        <Preprocessor>
            <Define String="_CRT_SECURE_NO_WARNINGS" />
        </Preprocessor>
    </Module>
</ModuleInfoEntry>
